ipyfilite/__init__.py
ipyfilite/_frontend.py
ipyfilite/_manager.py
ipyfilite/_version.py
ipyfilite/download/__init__.py
ipyfilite/download/fs.js
ipyfilite/http/__init__.py
ipyfilite/http/blob.js
ipyfilite/labextension/package.json
ipyfilite/labextension/static/122.1f769accd7c06dd3476f.js
ipyfilite/labextension/static/505.d468df3c1030ebc7a4e1.js
ipyfilite/labextension/static/509.10655dee3aacee464130.js
ipyfilite/labextension/static/885.e6915e175b17f74cdaf0.js
ipyfilite/labextension/static/remoteEntry.ebf7f0c3443cacd529af.js
ipyfilite/labextension/static/style.js
ipyfilite/labextension/static/third-party-licenses.json
ipyfilite/nbextension/extension.js
ipyfilite/nbextension/index.js
ipyfilite/nbextension/index.js.map
ipyfilite/tests/__init__.py
ipyfilite/tests/conftest.py
ipyfilite/tests/test_nbextension_path.py
ipyfilite/tests/test_upload.py
ipyfilite/upload/__init__.py
ipyfilite/upload/native.py
ipyfilite/upload/pyodide.py
ipyfilite-0.1.29.data/data/share/jupyter/labextensions/ipyfilite/package.json
ipyfilite-0.1.29.data/data/share/jupyter/labextensions/ipyfilite/static/122.1f769accd7c06dd3476f.js
ipyfilite-0.1.29.data/data/share/jupyter/labextensions/ipyfilite/static/505.d468df3c1030ebc7a4e1.js
ipyfilite-0.1.29.data/data/share/jupyter/labextensions/ipyfilite/static/509.10655dee3aacee464130.js
ipyfilite-0.1.29.data/data/share/jupyter/labextensions/ipyfilite/static/885.e6915e175b17f74cdaf0.js
ipyfilite-0.1.29.data/data/share/jupyter/labextensions/ipyfilite/static/remoteEntry.ebf7f0c3443cacd529af.js
ipyfilite-0.1.29.data/data/share/jupyter/labextensions/ipyfilite/static/style.js
ipyfilite-0.1.29.data/data/share/jupyter/labextensions/ipyfilite/static/third-party-licenses.json
ipyfilite-0.1.29.data/data/share/jupyter/nbextensions/ipyfilite/extension.js
ipyfilite-0.1.29.data/data/share/jupyter/nbextensions/ipyfilite/index.js
ipyfilite-0.1.29.data/data/share/jupyter/nbextensions/ipyfilite/index.js.map
ipyfilite-0.1.29.dist-info/METADATA
ipyfilite-0.1.29.dist-info/WHEEL
ipyfilite-0.1.29.dist-info/licenses/LICENSE.txt
ipyfilite-0.1.29.dist-info/RECORD
